Metadata-Version: 2.1
Name: soda-core-oracle
Version: 3.5.6
License-File: LICENSE
Requires-Dist: soda-core==3.5.6
Requires-Dist: oracledb<3.0.0,>=1.1.1
